harlring/__init__.py
harlring/_unittest/__init__.py
harlring/_unittest/test_apollo_opr_util.py
harlring/_unittest/test_artifactory_lib_util.py
harlring/_unittest/test_case_config_parser_util.py
harlring/_unittest/test_logging_util.py
harlring/_unittest/test_loguru_util.py
harlring/_unittest/test_windows_os_util.py
harlring/apollo/__init__.py
harlring/apollo/apollo_opr_util.py
harlring/artifactory/__init__.py
harlring/artifactory/artifactory_lib_util.py
harlring/caseconfig/__init__.py
harlring/caseconfig/parser.py
harlring/confluence/__init__.py
harlring/confluence/confluence_util.py
harlring/git/__init__.py
harlring/jenkins/__init__.py
harlring/jenkins/jenkins_util.py
harlring/jira/__init__.py
harlring/jira/jira_util.py
harlring/log/__init__.py
harlring/log/logging_util.py
harlring/log/loguru_util.py
harlring/rds/__init__.py
harlring/rds/rds_api_util.py
harlring/reg/__init__.py
harlring/reg/reg_util.py
harlring/request/__init__.py
harlring/request/request_util.py
harlring/response/__init__.py
harlring/response/response_util.py
harlring/sse_cloud/__init__.py
harlring/sse_cloud/sse_cloud_util.py
harlring/svn/__init__.py
harlring/svn/svn_util.py
harlring/windows/__init__.py
harlring/windows/os_util.py
harlring/xml/__init__.py
harlring/xml/xml_util.py
HarlRing-1.0.0.dist-info/LICENSE
HarlRing-1.0.0.dist-info/METADATA
HarlRing-1.0.0.dist-info/WHEEL
HarlRing-1.0.0.dist-info/top_level.txt
HarlRing-1.0.0.dist-info/RECORD
