Metadata-Version: 2.1
Name: HarlRing
Version: 1.0.0
Summary: UNKNOWN
Home-page: UNKNOWN
Author: peixiaodong
Author-email: pxd7th@vip.qq.com
License: MIT Licence
Platform: UNKNOWN
Requires-Python: >=3.6.0
License-File: LICENSE
Requires-Dist: twine (==3.8.0)
Requires-Dist: loguru (==0.6.0)
Requires-Dist: rsa (==4.9)
Requires-Dist: artifactory (==0.1.17)
